SortPy/__init__.py
SortPy/bubble_sort.py
SortPy/heap_sort.py
SortPy/insertion_sort.py
SortPy/merge_sort.py
SortPy/quick_sort.py
SortPy/selection_sort.py
SortPy3-0.0.0.dist-info/METADATA
SortPy3-0.0.0.dist-info/WHEEL
SortPy3-0.0.0.dist-info/top_level.txt
SortPy3-0.0.0.dist-info/RECORD
