Metadata-Version: 2.1
Name: SortPy3
Version: 0.0.0
Summary: A Python package providing efficient sorting algorithms like Bubble Sort, Insertion Sort, Merge Sort, Selection Sort, Heap Sort, and Quick Sort.
Home-page: https://github.com/Ashhad776/SortPy3
Author: Ashhad Ahmed
Author-email: ashhadahmed776@gmail.com
Classifier: Development Status :: 3 - Alpha
Classifier: Intended Audience :: Developers
Classifier: Operating System :: OS Independent
Classifier: Programming Language :: Python :: 3
Classifier: Topic :: Software Development :: Libraries :: Python Modules
